{"cameraMode":{"drawMode":0,"name":"Shaded","section":"Shading Mode"},"sceneLighting":false,"audioPlay":false,"sceneViewState":{"m_AlwaysRefresh":false,"showFog":true,"showSkybox":false,"showFlares":true,"showImageEffects":true,"showParticleSystems":true,"showVisualEffectGraphs":true,"m_FxEnabled":true},"in2DMode":false,"pivot":{"x":6.940000057220459,"y":2.4521055221557619,"z":-10.536005973815918},"rotation":{"x":0.10806775093078613,"y":0.023853542283177377,"z":-0.0025985881220549347,"w":0.9938661456108093},"size":4.124216079711914,"orthographic":false}